adzerk_decision_sdk/__init__.py
adzerk_decision_sdk/api_client.py
adzerk_decision_sdk/client.py
adzerk_decision_sdk/configuration.py
adzerk_decision_sdk/enums.py
adzerk_decision_sdk/exceptions.py
adzerk_decision_sdk/model_utils.py
adzerk_decision_sdk/rest.py
adzerk_decision_sdk/api/__init__.py
adzerk_decision_sdk/api/decision_api.py
adzerk_decision_sdk/api/userdb_api.py
adzerk_decision_sdk/apis/__init__.py
adzerk_decision_sdk/models/__init__.py
adzerk_decision_sdk/models/consent_request.py
adzerk_decision_sdk/models/content.py
adzerk_decision_sdk/models/decision.py
adzerk_decision_sdk/models/decision_request.py
adzerk_decision_sdk/models/decision_response.py
adzerk_decision_sdk/models/event.py
adzerk_decision_sdk/models/matched_point.py
adzerk_decision_sdk/models/placement.py
adzerk_decision_sdk/models/pricing_data.py
adzerk_decision_sdk/models/user.py
adzerk_decision_sdk-1.0.0b19.dist-info/licenses/LICENSE
adzerk_decision_sdk-1.0.0b19.dist-info/METADATA
adzerk_decision_sdk-1.0.0b19.dist-info/WHEEL
adzerk_decision_sdk-1.0.0b19.dist-info/top_level.txt
adzerk_decision_sdk-1.0.0b19.dist-info/RECORD
