Metadata-Version: 2.4
Name: adzerk-decision-sdk
Version: 1.0.0b19
Summary: Adzerk Decision SDK
Home-page: https://github.com/adzerk/adzerk-decision-sdk-python
Author: Adzerk
Author-email: engineering@adzerk.com
Keywords: adzerk,Adzerk Decision SDK
License-File: LICENSE
Requires-Dist: urllib3>=1.15
Requires-Dist: six>=1.10
Requires-Dist: certifi
Requires-Dist: python-dateutil
Dynamic: author
Dynamic: author-email
Dynamic: description
Dynamic: home-page
Dynamic: keywords
Dynamic: license-file
Dynamic: requires-dist
Dynamic: summary
